face_pipeline.py
face_pipeline-0.0.13.dist-info/METADATA
face_pipeline-0.0.13.dist-info/WHEEL
face_pipeline-0.0.13.dist-info/entry_points.txt
face_pipeline-0.0.13.dist-info/top_level.txt
face_pipeline-0.0.13.dist-info/RECORD
